simplescheduler/__init__.py
simplescheduler/default_settings.py
simplescheduler/default_settings_test.py
simplescheduler/utils.py
simplescheduler/utils_test.py
simplescheduler/version.py
simplescheduler/corescheduler/__init__.py
simplescheduler/corescheduler/constants.py
simplescheduler/corescheduler/job.py
simplescheduler/corescheduler/scheduler_manager.py
simplescheduler/corescheduler/scheduler_manager_test.py
simplescheduler/corescheduler/utils.py
simplescheduler/corescheduler/core/__init__.py
simplescheduler/corescheduler/core/base.py
simplescheduler/corescheduler/core/base_test.py
simplescheduler/corescheduler/datastore/__init__.py
simplescheduler/corescheduler/datastore/base.py
simplescheduler/corescheduler/datastore/base_test.py
simplescheduler/corescheduler/datastore/tables.py
simplescheduler/corescheduler/datastore/providers/__init__.py
simplescheduler/corescheduler/datastore/providers/mysql.py
simplescheduler/corescheduler/datastore/providers/postgres.py
simplescheduler/corescheduler/datastore/providers/sqlite.py
simplescheduler/server/__init__.py
simplescheduler/server/server.py
simplescheduler/server/handlers/__init__.py
simplescheduler/server/handlers/audit_logs.py
simplescheduler/server/handlers/base.py
simplescheduler/server/handlers/executions.py
simplescheduler/server/handlers/executions_test.py
simplescheduler/server/handlers/index.py
simplescheduler/server/handlers/jobs.py
simplescheduler/server/handlers/jobs_test.py
simplescheduler/static/index.html
simplescheduler/static/css/main.css
simplescheduler/static/css/vendor/bootstrap-switch.css
simplescheduler/static/css/vendor/bootstrap.css
simplescheduler/static/css/vendor/bootstrap.css.map
simplescheduler/static/css/vendor/jquery.dataTables.css
simplescheduler/static/css/vendor/select2-bootstrap.css
simplescheduler/static/css/vendor/select2.css
simplescheduler/static/css/vendor/images/Sorting icons.psd
simplescheduler/static/css/vendor/images/back_disabled.png
openmetadata_simplescheduler-0.2.1.dist-info/LICENSE
openmetadata_simplescheduler-0.2.1.dist-info/METADATA
openmetadata_simplescheduler-0.2.1.dist-info/WHEEL
openmetadata_simplescheduler-0.2.1.dist-info/top_level.txt
openmetadata_simplescheduler-0.2.1.dist-info/RECORD
