Metadata-Version: 2.1
Name: openmetadata-simplescheduler
Version: 0.2.1
Summary: SimpleScheduler A Cron Library for Openmetadata
Home-page: https://open-metadata.org/
Author: OpenMetadata Committers
License: Apache License 2.0
Project-URL: Documentation, https://docs.open-metadata.org/
Project-URL: Source, https://github.com/open-metadata/simplescheduler
Platform: UNKNOWN
Classifier: Development Status :: 5 - Production/Stable
Classifier: License :: OSI Approved :: BSD License
Classifier: Topic :: System :: Distributed Computing
Classifier: Topic :: Software Development :: Object Brokering
Classifier: Programming Language :: Python
Classifier: Programming Language :: Python :: 2.7
Classifier: Programming Language :: Python :: 3.3
Classifier: Programming Language :: Python :: 3.4
Classifier: Programming Language :: Python :: 3.5
Classifier: Programming Language :: Python :: 3.6
Classifier: Programming Language :: Python :: Implementation :: CPython
Classifier: Operating System :: OS Independent
Requires-Python: >=3.8
License-File: LICENSE
Requires-Dist: APScheduler (>=3.0.0)
Requires-Dist: SQLAlchemy (>=1.0.0)
Requires-Dist: future (>=0.15.2)
Requires-Dist: tornado (<6)
Requires-Dist: python-dateutil (>=2.2)
Provides-Extra: python_version_3.3_
Requires-Dist: funcsigs ; extra == 'python_version_3.3_'
